<?xml version="1.0" encoding="utf-8" ?>
<Override>
<sounds>
    <!--<startupsound file="Content/Sounds/StartDrone.ogg"/>-->

    <!--
    <music file="Content/Sounds/Music/Simplex.ogg" type="default"/>
    <music file="Content/Sounds/Music/Tenebrous Brothers Carnival - Prelude.ogg" type="default"/>
    -->

    <music file="%ModDir%/Sounds/BGM/Touhou Deep Sea Operation Team Main Menu01.ogg" type="menu" continuefromprevioustime="true"/>
    <music file="%ModDir%/Sounds/BGM/Touhou_Treasure_CD03.ogg" type="menu" continuefromprevioustime="true"/>

    <music file="%ModDir%/Sounds/BGM/Touhou Deep Sea Operation Team Default01.ogg" type="editor" continuefromprevioustime="true"/>

    <music file="%ModDir%/Sounds/BGM/Touhou_Treasure_CD04.ogg" type="endbossfight" volume="0.5"/>

    <music file="%ModDir%/Sounds/BGM/Touhou_Treasure_CD02.ogg" type="city" volume="0.2"/>

</sounds>
</Override>
